pyshic/__init__.py
pyshic/brewersza/__init__.py
pyshic/brewersza/brewersza.py
pyshic/brewersza/moonsza.py
pyshic/juliandate/__init__.py
pyshic/juliandate/juliandate.py
pyshic/math/falt_spec.py
pyshic/spectral_ops/__init__.py
pyshic/spectral_ops/spec_ops.py
pyshic-0.0.2.dist-info/LICENSE
pyshic-0.0.2.dist-info/METADATA
pyshic-0.0.2.dist-info/WHEEL
pyshic-0.0.2.dist-info/top_level.txt
pyshic-0.0.2.dist-info/RECORD
